thebigselector/__init__.py
thebigselector/__version__.py
thebigselector/thebigselector.py
thebigselector-1.0.1.dist-info/LICENSE
thebigselector-1.0.1.dist-info/METADATA
thebigselector-1.0.1.dist-info/NOTICE
thebigselector-1.0.1.dist-info/WHEEL
thebigselector-1.0.1.dist-info/top_level.txt
thebigselector-1.0.1.dist-info/RECORD
