Metadata-Version: 2.1
Name: thebigselector
Version: 1.0.1
Summary: A Tkinter text widget based option selector.
Home-page: https://github.com/kantal/thebigselector
Author: Antal Koós
Author-email: k2osgak@gmail.com
License: MIT
Project-URL: Doc and source, https://github.com/kantal/thebigselector
Keywords: tkinter,graphics,widget
Platform: UNKNOWN
Classifier: Programming Language :: Python :: 3
Classifier: License :: OSI Approved :: MIT License
Classifier: Operating System :: OS Independent
Requires-Python: >=3.8
